setup.py
eko_probability/Binomialdistribution.py
eko_probability/Gaussiandistribution.py
eko_probability/Generaldistribution.py
eko_probability/__init__.py
eko_probability.egg-info/PKG-INFO
eko_probability.egg-info/SOURCES.txt
eko_probability.egg-info/dependency_links.txt
eko_probability.egg-info/not-zip-safe
eko_probability.egg-info/top_level.txt