Metadata-Version: 1.0
Name: eko-probability
Version: 0.1
Summary: Gaussian and Binomial distributions
Home-page: UNKNOWN
Author: Nurudeen Adesina
Author-email: access2abey@gmail.com
License: UNKNOWN
Platform: UNKNOWN
